mariya_endostats/__init__.py
mariya_endostats/endo_stats.py
dayana_endostat-0.1.0.dist-info/LICENSE
dayana_endostat-0.1.0.dist-info/METADATA
dayana_endostat-0.1.0.dist-info/WHEEL
dayana_endostat-0.1.0.dist-info/top_level.txt
dayana_endostat-0.1.0.dist-info/RECORD
