Metadata-Version: 2.1
Name: dayana-endostat
Version: 0.1.0
Summary: A library for clinical & statistical calculations in Endodontics
Author: Ashik Sanyo
Author-email: ashiksanyo01@gmail.com
Classifier: Programming Language :: Python :: 3
Classifier: License :: OSI Approved :: MIT License
Classifier: Operating System :: OS Independent
Requires-Python: >=3.6
License-File: LICENSE
Requires-Dist: numpy
